vio/Vio.py
vio/__init__.py
Vio-0.0.12.dist-info/LICENSE
Vio-0.0.12.dist-info/METADATA
Vio-0.0.12.dist-info/WHEEL
Vio-0.0.12.dist-info/top_level.txt
Vio-0.0.12.dist-info/RECORD
