Metadata-Version: 2.1
Name: Vio
Version: 0.0.12
Summary: A Wrapper for the Vio API
Home-page: https://viopy.rtfd.io
Author: Meaning
License: MIT
Platform: UNKNOWN
Classifier: Development Status :: 1 - Planning
Classifier: License :: OSI Approved :: MIT License
Classifier: Programming Language :: Python :: 3.8
Classifier: Programming Language :: Python :: 3.9
Classifier: Programming Language :: Python :: 3.10
Classifier: Typing :: Typed
License-File: LICENSE
Requires-Dist: websockets (==10.3)
Requires-Dist: httpx (==0.22.0)
Requires-Dist: terminaltables (==3.1.10)
